odoo/addons/ssi_rma_sale/README.rst
odoo/addons/ssi_rma_sale/__init__.py
odoo/addons/ssi_rma_sale/__manifest__.py
odoo/addons/ssi_rma_sale/i18n/ssi_rma_sale.pot
odoo/addons/ssi_rma_sale/models/__init__.py
odoo/addons/ssi_rma_sale/models/rma_customer_line.py
odoo/addons/ssi_rma_sale/models/stock_rule.py
odoo/addons/ssi_rma_sale/static/description/icon.png
odoo/addons/ssi_rma_sale/views/rma_customer_views.xml
odoo14_addon_ssi_rma_sale-14.0.1.1.2.dist-info/METADATA
odoo14_addon_ssi_rma_sale-14.0.1.1.2.dist-info/WHEEL
odoo14_addon_ssi_rma_sale-14.0.1.1.2.dist-info/top_level.txt
odoo14_addon_ssi_rma_sale-14.0.1.1.2.dist-info/RECORD
